bitlogclient/__init__.py
bitlogclient/report.py
bitlogclient/token.py
nn_bitlog_client-0.0.3.dist-info/LICENSE
nn_bitlog_client-0.0.3.dist-info/METADATA
nn_bitlog_client-0.0.3.dist-info/WHEEL
nn_bitlog_client-0.0.3.dist-info/top_level.txt
nn_bitlog_client-0.0.3.dist-info/RECORD
