Metadata-Version: 2.1
Name: nn-bitlog-client
Version: 0.0.3
Summary: Python SDK for BitlogWMS API
Author: Nordic Nest
License: License text copyright (c) 2020 MariaDB Corporation Ab, All Rights Reserved.
Classifier: Programming Language :: Python :: 3
Classifier: Operating System :: OS Independent
Requires-Python: >=3.8
License-File: LICENSE
Requires-Dist: requests
